Brysk_Task/__init__.py
Brysk_Task/app.py
Brysk_Task/app_opt.py
Brysk_Task/class_names.py
Brysk_Task/main.py
Brysk_Task/test_home_route.py
Brysk_Task-0.1.dist-info/LICENSE.txt
Brysk_Task-0.1.dist-info/METADATA
Brysk_Task-0.1.dist-info/WHEEL
Brysk_Task-0.1.dist-info/top_level.txt
Brysk_Task-0.1.dist-info/RECORD
