Metadata-Version: 2.1
Name: Brysk-Task
Version: 0.1
Summary: A Python module with an API to perform object detection on videos using a YOLO model optimized with OpenVINO.
Author: Romasha Guin
Author-email: guinromasha@gmail.com
Classifier: Programming Language :: Python :: 3
Classifier: License :: OSI Approved :: MIT License
Classifier: Operating System :: OS Independent
License-File: LICENSE.txt
